LICENSE
MANIFEST.in
README.rst
release.txt
setup.py
bin/rpn
bin/rpn.bat
rpn_calculator/__init__.py
rpn_calculator/rpn.py
rpn_calculator.egg-info/PKG-INFO
rpn_calculator.egg-info/SOURCES.txt
rpn_calculator.egg-info/dependency_links.txt
rpn_calculator.egg-info/requires.txt
rpn_calculator.egg-info/top_level.txt