Metadata-Version: 1.1
Name: rpn-calculator
Version: 1.2.1.3
Summary: RPN calculator for CLI
Home-page: https://github.com/massongit/rpn-calculator
Author: Masaya SUZUKI
Author-email: suzukimasaya428@gmail.com
License: MIT
Keywords: RPN Calculator
Platform: UNKNOWN
Classifier: Environment :: Console
Classifier: Programming Language :: Python :: 2.7
Classifier: Programming Language :: Python :: 3.2
Classifier: Programming Language :: Python :: 3.3
Classifier: Programming Language :: Python :: 3.4
Classifier: Programming Language :: Python :: 3.5
Classifier: Programming Language :: Python :: 3.6
